mubelnet/__init__.py
mubelnet/_surgery.py
mubelnet/calibration.py
mubelnet/initializers.py
mubelnet/layers.py
mubelnet/mcmc.py
mubelnet/multinomial.py
mubelnet/nets.py
mubelnet/poisson.py
mubelnet/random.py
mubelnet/sugar.py
mubelnet/utils.py
mubelnet-1.0.0.dist-info/METADATA
mubelnet-1.0.0.dist-info/WHEEL
mubelnet-1.0.0.dist-info/licenses/LICENSE.txt
mubelnet-1.0.0.dist-info/RECORD
