Metadata-Version: 2.3
Name: mubelnet
Version: 1.0.0
Summary: Deep Bayesian unsupervised decoder networks. Use poisson or multinomial belief networks to cluster count data.
Project-URL: Homepage, https://gitlab.com/hylkedonker/mubelnet
Project-URL: Bug Tracker, https://gitlab.com/hylkedonker/mubelnet/-/issues
Author-email: "Hylke C. Donker" <h.c.donker@umcg.nl>, Dorien Neijzen <d.neijzen@umcg.nl>
License-File: LICENSE.txt
Classifier: License :: OSI Approved :: MIT License
Classifier: Operating System :: OS Independent
Classifier: Programming Language :: Python :: 3
Requires-Python: >=3.10
Requires-Dist: chex
Requires-Dist: dm-haiku
Requires-Dist: einops
Requires-Dist: flax
Requires-Dist: jax
Requires-Dist: jaxtyping
Requires-Dist: matplotlib
Requires-Dist: tensor-annotations
Requires-Dist: tensor-annotations-jax-stubs
Requires-Dist: tfp-nightly
